MANIFEST.in
setup.cfg
setup.py
CFS_Manager.egg-info/PKG-INFO
CFS_Manager.egg-info/SOURCES.txt
CFS_Manager.egg-info/dependency_links.txt
CFS_Manager.egg-info/entry_points.txt
CFS_Manager.egg-info/not-zip-safe
CFS_Manager.egg-info/requires.txt
CFS_Manager.egg-info/top_level.txt
cfs_manager/box_wrapper.py
cfs_manager/cfs_watcher.py
cfs_manager/cli.py
cfs_manager/configuration.py
cfs_manager/dropbox_wrapper.py
cfs_manager/file_systems.py
cfs_manager/gdrive_wrapper.py
cfs_manager/help_functions.py
cfs_manager/manager.py
cfs_manager/pcloud_wrapper.py
cfs_manager/settings.yaml
cfs_manager/zipper.py
docs/README.rst
docs/about.rst
docs/changelog.rst
docs/contributor_notes.rst
docs/direction.rst
docs/faq.rst
docs/features.rst
docs/index.rst
docs/license.rst
tests/test_cli.py
tests/test_manager.py