Metadata-Version: 1.1
Name: CFS-Manager
Version: 1.3.0
Summary: A virtual filesystem for accessing storage on multiple cloud services.
Home-page: https://github.com/alisonstreete/cfs-manager
Author: Alison Streete
Author-email: alison.streete@gmail.com
License: Apache License 2.0
Platform: UNKNOWN
Classifier: Development Status :: 4 - Beta
Classifier: License :: OSI Approved :: Apache Software License
Classifier: Operating System :: OS Independent
Classifier: Programming Language :: Python :: 3
Classifier: Programming Language :: Python :: 3.6
Classifier: Programming Language :: Python :: Implementation :: CPython
Classifier: Natural Language :: English
Classifier: Environment :: Console
Classifier: Topic :: System :: Archiving :: Mirroring
Classifier: Intended Audience :: End Users/Desktop
